{"Semester 1": {"A": ["Band 9/10 Odd", NaN, "Pe 10 Odd", "Eng 9", "Int/Web 9/10", "Math 10 \u2013 210", "Chem 11", "SS 9", NaN, "Prec 12H", "Eng 9", "Eng 12", "Phy 12", "Cr. Writing 10", "Prec 11 \u2013 205B", "SS 11", NaN, "PE 9/10", "New Media 11 211", "Library", "Phy 11", "Comp Cul 12", NaN, NaN, "EN 10C", "CLE 10", NaN, "InDesign 9-12", "PE 9 (Even)", "SS 11C", "Dance Found 9-12", "ART 9/10", "Life Sc 11", "Mark 11 (Combo)", "Foods 11/12", "SS10", NaN, "Wood 9-12", "Clim Change 12", "PreC 12", NaN, NaN, "Active Liv 11/12G", "Sc 10", NaN, "Aviation", NaN, "Comp Sci 11/12", "Anatomy 12", "Med Des 10-12", NaN, NaN], "B": ["Band 11/12 Odd", "Prec 11", NaN, NaN, NaN, NaN, NaN, "SS11", "Sp 9/10", "Prec12", "Sc 9", "Cr.Writing 10", "Stats 12", "Eng 12", "Math 10 \u2013 205B", "Law 12", "Phy 11", "SS 10", "Comp 11 121", "Library", "Math 10C", "Comp Cul 12", "Inclusive Ed", "Anatomy 12", NaN, "ACCT 11 - 113", "ELL 10-12 \u2013 A7", "Drafting 9-12", "Active Liv 11/12", NaN, "Yoga 9-12", "CLE 10 - 201", NaN, "Ent 12 (Combo)", "Foods 11/12", "Eng 10 ELL/ISP", "FR 9", "Auto 11/12", "Math 9", "Math 9C", NaN, "Math 10H", "PE 9/10G", "Sc 10", "Sc 9", "Aviation", "CLE 10 \u2013 Even 114", "Comp Sc 12", "Chem 12", NaN, "Cr.Writing 11", NaN], "C": ["Guitar 10-12", "Prec 12", "PE 91/0B", "Lit Studies 11", "Int/Web 9/10", "Sc 10 \u2013 116", "Env Sc 11", "HIS 12", "Italian 11/Intro", "Prec 11H", "Inclusive Ed", "Eng 12", "Phy 12", NaN, "Math 9 \u2013 205B", "SS 11", "Phy 11", NaN, "New Media 11 122", "Library", "Math 10C", NaN, NaN, "Anatomy 12", "AP Lit Studies 12", "CLE 10", "New Media 10 A5", "Drafting 9-12", "SS9 - 211", "SS 9C", NaN, "Photo 10-12 - 113", "CHEM 11", NaN, "Foods 9/10", "Eng 10 ELL/ISP", "FR 11/12", NaN, "Numeracy 9", "Math 9C", NaN, "Psych 11", "PE 9/10", "WPM 10", NaN, "Aviation", NaN, "Comp Sc 11", "Chem 12", "Robotics 9-12", "Lit Stud 11C", "Eng 12 ELL"], "D": [NaN, "Prec 12", "Law 12 - 123", "Eng 9", "Comp Prog 11", "Math 10 - 220", "Sc 9", NaN, "SP 11", NaN, "Inclusive Ed", "Comp 11", "AP Phy 12", "Eng 12", "FOM 11 \u2013 205B", "Law 12", "Chem 11", "Crim 12", NaN, "Library", "Prec 11", NaN, "Sc 10 - 227", "Anatomy 12", "Eng 10C", "Marketing 10 \u2013 203", "Eng 9 -122", NaN, "PE 9/10B", "SS 9C", NaN, "ART 9-12", "Life Sc 11", "Mark 10", "Foods 9/10", "SS 10", "FR 10", "Mech 9/10", "Clim Change 12", "WPM 11", NaN, "Psych 11", "PE 9/10G", "Sc 10", NaN, "Aviation", "CLE 10 - 201", NaN, "Chem 11", "Robotics 9-12", "Drama 11/12", "Eng 12 ELL"], "OUT OF TIMETABLE": ["Jazz/choir", "Scholarship", NaN, NaN, NaN, NaN, NaN, NaN, "Comm Lead", "Geom/ Peer T", NaN, NaN, NaN, NaN, NaN, NaN, NaN, NaN, NaN, NaN, NaN, NaN, NaN, "Env Lead", NaN, NaN, NaN, NaN, NaN, "Challenge", "Chor 9-12", NaN, NaN, NaN, NaN, NaN, NaN, NaN, NaN, NaN, "Strings", NaN, NaN, NaN, NaN, NaN, "CLC, WEx, F.Aid", "Yearbook", NaN, NaN, NaN, NaN]}, "Semester 2": {"A": ["Band 9 E/10 Odd", "Calc 12", "PE 10 Odd (Band)", "Comp 11", "Int/Web 9/10", "Math 9 \u2013 220", NaN, "Chem 11", "SS 11", "CLE 10 - 201", NaN, "SP 9", NaN, NaN, NaN, "Eng 12", "Math 10", "Law 12", NaN, "Crim 12", NaN, "Library", NaN, "History 12", "SC 10C", "AP Eng 12", "ENT 12 \u2013 113", "FOM 11 \u2013 212", "Drafting 9-12", "PE 9 (Even)", "SS 11C", "HIP HOP 9-12", "ART 10-12", "Life Sc 11", "Foods 9/10", "Comp Cul 12", NaN, "New Media 10", "Mech 9/10", "Prec 11", "Anatomy 12", NaN, "Psych 11", "PE 9/10G", "SC 10", NaN, NaN, "Comp Sci 11/12", "Chem 12", "Robotics 9-12 104", "Eng 9C", NaN], "B": ["Band 11/12 Odd", "AP Calc 12", "Law 12", "Eng 9 ELL", "Int/Web 9/10", "Sc 9 \u2013 216", NaN, NaN, "SS9", "Marketing 10 - 205B", NaN, "SP 10", NaN, "Eng 12", "Phy 12", "Cr. Writing 10", NaN, NaN, "Phy 11", "SS 10", "CLE 10 \u2013 104", "Library", "SC 9C", "History 12", "SC 10C", NaN, "Acc 11/12 \u2013 201", NaN, "Drafting 9-12", "PE 9/10B", NaN, "DANCE T&P9-12", NaN, "Life Sc 11", "Foods 11/12", "Eng 10 ELL/ISP", NaN, "FR 11", "Auto 11/12", "Prec 11", "Chem 12", NaN, NaN, "Fit Cond 11/12", "SC 10", "Skills 10-12", "CLE 10 Linear(Band) even", "Comp Prog 11/12", "Chem 11", "Media Des 10-12 - 113", "Drama 9/10", NaN], "C": ["Guitar 9-12", NaN, "PE 9/10", "Lit Stud 11C", "Dig Media 12", "Sc 10 \u2013 219", "SS 10 \u2013 209", "Chem 11", "SS9", "CLE 10 - 201", NaN, NaN, "Prec12", "Comp 11", "Calc 12", "Eng 12", "Math 9", "Law 12", "Phy 11", "Crim 12", "New Media10 122", "Library", "SC 9C", NaN, NaN, "Eng 12C", "Acc 11 \u2013 203", NaN, "Outdoor Ed 10-12 - 104", "Active Living 11/12", "SS 10C", NaN, "ART 9-12", "Life Sc 11", "Food 11/12", "Eng 10 ELL/ISP", NaN, "FR 9", NaN, "Prec 11", NaN, NaN, "Math 10", NaN, "SC 9", "Wood 9-12", "Geo 12 - 214", NaN, "Chem 12", "Comp 10/11 - 113", "Eng 9", "Eng 12YL"], "D": [NaN, NaN, "PE 9/10B", "Eng 9", "Comp Sc 11", "Sc 10 - 225", "SS10 - 211", "Env Sc 11", NaN, "CLE 10 - 201", "SS 10 - 123", "SP 11/12", "Chem 12", "Eng 12", "Phy 12", "Cr. Writing 10", "Prec 11", "SS 11", "Photo 10-12", NaN, "Cr.Writing 11 \u2013 122", "Library", "Phy 11", NaN, "Anatomy 12", "Comp 11", "Ent 12 \u2013 221", NaN, NaN, "SS 9 - 106", "SS 10C", NaN, "ART 9/10", "Chem 11", NaN, NaN, NaN, "FR 11/12", "Auto 11/12", NaN, "Prec 12", NaN, "WPM 11", "PE 9/10G", NaN, "Wood 9-12", NaN, "Comp Sc 12 AP", NaN, "Draft 9-12 - 105", "Eng 9C", "Eng 12YL"], "OUT OF TIMETABLE": ["Jazz/choir", "Scholarship", NaN, NaN, NaN, NaN, NaN, NaN, NaN, NaN, NaN, "Comm Lead", "Geom/ Peer T", NaN, NaN, NaN, NaN, NaN, NaN, NaN, NaN, NaN, NaN, NaN, "Env Lead", NaN, NaN, NaN, NaN, NaN, "Challenge", "Chor 9-12/L", NaN, NaN, NaN, NaN, "Leadership", NaN, NaN, NaN, NaN, "Strings", NaN, NaN, NaN, NaN, "CLC, WEX, F.Aid", "Yearbook", NaN, NaN, NaN, NaN]}}